mcp_ashare_quant/__init__.py
mcp_ashare_quant/__main__.py
mcp_ashare_quant/ashare.py
mcp_ashare_quant/mytt.py
mcp_ashare_quant/recommend.py
mcp_ashare_quant/server.py
mcp_ashare_quant/stock_mapping.json
mcp_ashare_quant/test.py
mcp_ashare_quant-0.1.7.dist-info/licenses/LICENSE
mcp_ashare_quant-0.1.7.dist-info/METADATA
mcp_ashare_quant-0.1.7.dist-info/WHEEL
mcp_ashare_quant-0.1.7.dist-info/entry_points.txt
mcp_ashare_quant-0.1.7.dist-info/top_level.txt
mcp_ashare_quant-0.1.7.dist-info/RECORD
