Metadata-Version: 2.4
Name: mcp-ashare-quant
Version: 0.1.7
Summary: MCP协议的A股量化分析工具，为AI Agent提供股票推荐、行情分析、K线图绘制等功能
Author-email: fengjinchao <your.email@example.com>
Maintainer-email: fengjinchao <your.email@example.com>
License: Apache2.0 License
Project-URL: Homepage, https://github.com/fengjinchao/mcp-ashare-quant
Project-URL: Repository, https://github.com/fengjinchao/mcp-ashare-quant
Project-URL: Documentation, https://github.com/fengjinchao/mcp-ashare-quant#readme
Project-URL: Bug Tracker, https://github.com/fengjinchao/mcp-ashare-quant/issues
Keywords: mcp,stock,quant,a-share,finance,ai-agent
Classifier: Development Status :: 3 - Alpha
Classifier: Intended Audience :: Developers
Classifier: Intended Audience :: Financial and Insurance Industry
Classifier: License :: OSI Approved :: MIT License
Classifier: Operating System :: OS Independent
Classifier: Programming Language :: Python :: 3
Classifier: Programming Language :: Python :: 3.10
Classifier: Programming Language :: Python :: 3.11
Classifier: Programming Language :: Python :: 3.12
Classifier: Topic :: Office/Business :: Financial
Classifier: Topic :: Scientific/Engineering :: Information Analysis
Requires-Python: >=3.10
License-File: LICENSE
Requires-Dist: httpx>=0.28.1
Requires-Dist: matplotlib>=3.10.1
Requires-Dist: mcp[cli]>=1.5.0
Requires-Dist: mplfinance>=0.12.10b0
Requires-Dist: pandas>=2.2.3
Requires-Dist: requests>=2.32.3
Dynamic: license-file
